pyEarnapp/__init__.py
pyEarnapp/earnapp.py
pyEarnapp/errors.py
pyEarnapp/report.py
pyEarnapp/tools.py
pyEarnapp/models/__init__.py
pyEarnapp/models/device.py
pyEarnapp/models/earnings.py
pyEarnapp/models/endpoints.py
pyEarnapp/models/header.py
pyEarnapp/models/referral.py
pyEarnapp/models/transactions.py
pyEarnapp/models/user.py
pyEarnapp-0.0.16.1.dist-info/METADATA
pyEarnapp-0.0.16.1.dist-info/WHEEL
pyEarnapp-0.0.16.1.dist-info/top_level.txt
pyEarnapp-0.0.16.1.dist-info/RECORD
