Metadata-Version: 2.1
Name: pyEarnapp
Version: 0.0.16.1
Summary: UNOFFICIAL Python bindings for Earnapp dashboard API
Home-page: https://github.com/fazalfarhan01/EarnApp-API
Author: fazalfarhan01 (Mohamed Farhan Fazal)
Author-email: fazal@ffehost.com
License: UNKNOWN
Project-URL: Bug Tracker, https://github.com/fazalfarhan01/EarnApp-API/issues
Keywords: python,earnapp,passive income,earnapp api,earnapp dashboard,requests,python earnapp
Platform: UNKNOWN
Classifier: Development Status :: 5 - Production/Stable
Classifier: Intended Audience :: Developers
Classifier: Programming Language :: Python :: 3
Classifier: Operating System :: OS Independent
Requires-Dist: requests
